<?xml version='1.0' encoding='UTF-8' ?>
<export>
<header>
  <corpus>user/sandrayoung/web_webgnrd</corpus>
  <subcorpus>-</subcorpus>
</header>
<wordsketch>
  <keyword pos="" freq="0">Crepidostomum</keyword>
  <gramrel name="modifiers of X" hits="1" score="5.880">
    <coll hits="1" score="13.990" query="w1775283456">Bunodera</coll>
  </gramrel>
  <gramrel name="nouns modified by X" hits="8" score="47.060">
    <coll hits="5" score="13.510" query="w1775292224">farionis</coll>
    <coll hits="2" score="12.680" query="w1775292226">metoecus</coll>
    <coll hits="1" score="11.830" query="w1775292225">meteocus</coll>
  </gramrel>
</wordsketch>
</export>
