<?xml version='1.0' encoding='UTF-8' ?>
<export>
<header>
  <corpus>user/sandrayoung/web_webgnrd</corpus>
  <subcorpus>-</subcorpus>
</header>
<wordsketch>
  <keyword pos="" freq="0">mirabilis</keyword>
  <gramrel name="modifiers of X" hits="7" score="50.000">
    <coll hits="5" score="13.620" query="w1969608640">Gillichthys</coll>
    <coll hits="2" score="12.830" query="w1969608641">Phenacobius</coll>
  </gramrel>
  <gramrel name="nouns modified by X" hits="2" score="14.290">
    <coll hits="2" score="13.000" query="w1969635904">Gobiidae</coll>
  </gramrel>
  <gramrel name="X and/or ..." hits="2" score="14.290">
    <coll hits="2" score="13.410" query="w1969591360">Gobiidae</coll>
  </gramrel>
</wordsketch>
</export>
